[{"timestamp": "1", "id": "1", "name": "1.txt"}, {"timestamp": "2", "id": "2", "name": "2.txt"}, {"timestamp": "3", "id": "3", "name": "3.txt"}, {"timestamp": "4", "id": "4", "name": "4.txt"}, {"timestamp": "5", "id": "5", "name": "5.txt"}, {"timestamp": "6", "id": "6", "name": "6.txt"}, {"timestamp": "7", "id": "7", "name": "7.txt"}, {"timestamp": "8", "id": "8", "name": "8.txt"}, {"timestamp": "9", "id": "9", "name": "9.txt"}, {"timestamp": "10", "id": "10", "name": "10.txt"}, {"timestamp": "11", "id": "11", "name": "11.txt"}, {"timestamp": "12", "id": "12", "name": "12.txt"}, {"timestamp": "13", "id": "13", "name": "13.txt"}, {"timestamp": "14", "id": "14", "name": "14.txt"}, {"timestamp": "15", "id": "15", "name": "15.txt"}, {"timestamp": "16", "id": "16", "name": "16.txt"}, {"timestamp": "17", "id": "17", "name": "17.txt"}, {"timestamp": "18", "id": "18", "name": "18.txt"}, {"timestamp": "19", "id": "19", "name": "19.txt"}, {"timestamp": "20", "id": "20", "name": "20.txt"}, {"timestamp": "21", "id": "21", "name": "21.txt"}, {"timestamp": "22", "id": "22", "name": "22.txt"}, {"timestamp": "23", "id": "23", "name": "23.txt"}, {"timestamp": "24", "id": "24", "name": "24.txt"}, {"timestamp": "25", "id": "25", "name": "25.txt"}, {"timestamp": "26", "id": "26", "name": "26.txt"}, {"timestamp": "27", "id": "27", "name": "27.txt"}, {"timestamp": "28", "id": "28", "name": "28.txt"}, {"timestamp": "29", "id": "29", "name": "29.txt"}, {"timestamp": "30", "id": "30", "name": "30.txt"}, {"timestamp": "31", "id": "31", "name": "31.txt"}, {"timestamp": "32", "id": "32", "name": "32.txt"}, {"timestamp": "33", "id": "33", "name": "33.txt"}, {"timestamp": "34", "id": "34", "name": "34.txt"}, {"timestamp": "35", "id": "35", "name": "35.txt"}, {"timestamp": "36", "id": "36", "name": "36.txt"}, {"timestamp": "37", "id": "37", "name": "37.txt"}, {"timestamp": "38", "id": "38", "name": "38.txt"}, {"timestamp": "39", "id": "39", "name": "39.txt"}, {"timestamp": "40", "id": "40", "name": "40.txt"}, {"timestamp": "41", "id": "41", "name": "41.txt"}, {"timestamp": "42", "id": "42", "name": "42.txt"}, {"timestamp": "43", "id": "43", "name": "43.txt"}, {"timestamp": "44", "id": "44", "name": "44.txt"}, {"timestamp": "45", "id": "45", "name": "45.txt"}, {"timestamp": "46", "id": "46", "name": "46.txt"}, {"timestamp": "47", "id": "47", "name": "47.txt"}, {"timestamp": "48", "id": "48", "name": "48.txt"}, {"timestamp": "49", "id": "49", "name": "49.txt"}, {"timestamp": "50", "id": "50", "name": "50.txt"}, {"timestamp": "51", "id": "51", "name": "51.txt"}, {"timestamp": "52", "id": "52", "name": "52.txt"}, {"timestamp": "53", "id": "53", "name": "53.txt"}, {"timestamp": "54", "id": "54", "name": "54.txt"}, {"timestamp": "55", "id": "55", "name": "55.txt"}, {"timestamp": "56", "id": "56", "name": "56.txt"}, {"timestamp": "57", "id": "57", "name": "57.txt"}, {"timestamp": "58", "id": "58", "name": "58.txt"}, {"timestamp": "59", "id": "59", "name": "59.txt"}, {"timestamp": "60", "id": "60", "name": "60.txt"}, {"timestamp": "61", "id": "61", "name": "61.txt"}, {"timestamp": "62", "id": "62", "name": "62.txt"}, {"timestamp": "63", "id": "63", "name": "63.txt"}, {"timestamp": "64", "id": "64", "name": "64.txt"}, {"timestamp": "65", "id": "65", "name": "65.txt"}, {"timestamp": "66", "id": "66", "name": "66.txt"}, {"timestamp": "67", "id": "67", "name": "67.txt"}, {"timestamp": "68", "id": "68", "name": "68.txt"}, {"timestamp": "69", "id": "69", "name": "69.txt"}, {"timestamp": "70", "id": "70", "name": "70.txt"}, {"timestamp": "71", "id": "71", "name": "71.txt"}, {"timestamp": "72", "id": "72", "name": "72.txt"}, {"timestamp": "73", "id": "73", "name": "73.txt"}, {"timestamp": "74", "id": "74", "name": "74.txt"}, {"timestamp": "75", "id": "75", "name": "75.txt"}, {"timestamp": "76", "id": "76", "name": "76.txt"}, {"timestamp": "77", "id": "77", "name": "77.txt"}, {"timestamp": "78", "id": "78", "name": "78.txt"}, {"timestamp": "79", "id": "79", "name": "79.txt"}, {"timestamp": "80", "id": "80", "name": "80.txt"}, {"timestamp": "81", "id": "81", "name": "81.txt"}, {"timestamp": "82", "id": "82", "name": "82.txt"}, {"timestamp": "83", "id": "83", "name": "83.txt"}, {"timestamp": "84", "id": "84", "name": "84.txt"}, {"timestamp": "85", "id": "85", "name": "85.txt"}, {"timestamp": "86", "id": "86", "name": "86.txt"}, {"timestamp": "87", "id": "87", "name": "87.txt"}, {"timestamp": "88", "id": "88", "name": "88.txt"}, {"timestamp": "89", "id": "89", "name": "89.txt"}, {"timestamp": "90", "id": "90", "name": "90.txt"}, {"timestamp": "91", "id": "91", "name": "91.txt"}, {"timestamp": "92", "id": "92", "name": "92.txt"}, {"timestamp": "93", "id": "93", "name": "93.txt"}, {"timestamp": "94", "id": "94", "name": "94.txt"}, {"timestamp": "95", "id": "95", "name": "95.txt"}, {"timestamp": "96", "id": "96", "name": "96.txt"}, {"timestamp": "97", "id": "97", "name": "97.txt"}, {"timestamp": "98", "id": "98", "name": "98.txt"}, {"timestamp": "99", "id": "99", "name": "99.txt"}, {"timestamp": "100", "id": "100", "name": "100.txt"}, {"timestamp": "101", "id": "101", "name": "101.txt"}, {"timestamp": "102", "id": "102", "name": "102.txt"}, {"timestamp": "103", "id": "103", "name": "103.txt"}, {"timestamp": "104", "id": "104", "name": "104.txt"}, {"timestamp": "105", "id": "105", "name": "105.txt"}, {"timestamp": "106", "id": "106", "name": "106.txt"}, {"timestamp": "107", "id": "107", "name": "107.txt"}, {"timestamp": "108", "id": "108", "name": "108.txt"}, {"timestamp": "109", "id": "109", "name": "109.txt"}, {"timestamp": "110", "id": "110", "name": "110.txt"}, {"timestamp": "111", "id": "111", "name": "111.txt"}, {"timestamp": "112", "id": "112", "name": "112.txt"}, {"timestamp": "113", "id": "113", "name": "113.txt"}, {"timestamp": "114", "id": "114", "name": "114.txt"}, {"timestamp": "115", "id": "115", "name": "115.txt"}, {"timestamp": "116", "id": "116", "name": "116.txt"}, {"timestamp": "117", "id": "117", "name": "117.txt"}, {"timestamp": "118", "id": "118", "name": "118.txt"}, {"timestamp": "119", "id": "119", "name": "119.txt"}, {"timestamp": "120", "id": "120", "name": "120.txt"}, {"timestamp": "121", "id": "121", "name": "121.txt"}, {"timestamp": "122", "id": "122", "name": "122.txt"}, {"timestamp": "123", "id": "123", "name": "123.txt"}, {"timestamp": "124", "id": "124", "name": "124.txt"}, {"timestamp": "125", "id": "125", "name": "125.txt"}, {"timestamp": "126", "id": "126", "name": "126.txt"}, {"timestamp": "127", "id": "127", "name": "127.txt"}, {"timestamp": "128", "id": "128", "name": "128.txt"}, {"timestamp": "129", "id": "129", "name": "129.txt"}, {"timestamp": "130", "id": "130", "name": "130.txt"}, {"timestamp": "131", "id": "131", "name": "131.txt"}, {"timestamp": "132", "id": "132", "name": "132.txt"}, {"timestamp": "133", "id": "133", "name": "133.txt"}, {"timestamp": "134", "id": "134", "name": "134.txt"}, {"timestamp": "135", "id": "135", "name": "135.txt"}, {"timestamp": "136", "id": "136", "name": "136.txt"}, {"timestamp": "137", "id": "137", "name": "137.txt"}, {"timestamp": "138", "id": "138", "name": "138.txt"}, {"timestamp": "139", "id": "139", "name": "139.txt"}, {"timestamp": "140", "id": "140", "name": "140.txt"}, {"timestamp": "141", "id": "141", "name": "141.txt"}, {"timestamp": "142", "id": "142", "name": "142.txt"}, {"timestamp": "143", "id": "143", "name": "143.txt"}, {"timestamp": "144", "id": "144", "name": "144.txt"}, {"timestamp": "145", "id": "145", "name": "145.txt"}, {"timestamp": "146", "id": "146", "name": "146.txt"}, {"timestamp": "147", "id": "147", "name": "147.txt"}, {"timestamp": "148", "id": "148", "name": "148.txt"}, {"timestamp": "149", "id": "149", "name": "149.txt"}, {"timestamp": "150", "id": "150", "name": "150.txt"}, {"timestamp": "151", "id": "151", "name": "151.txt"}, {"timestamp": "152", "id": "152", "name": "152.txt"}, {"timestamp": "153", "id": "153", "name": "153.txt"}, {"timestamp": "154", "id": "154", "name": "154.txt"}, {"timestamp": "155", "id": "155", "name": "155.txt"}, {"timestamp": "156", "id": "156", "name": "156.txt"}, {"timestamp": "157", "id": "157", "name": "157.txt"}, {"timestamp": "158", "id": "158", "name": "158.txt"}, {"timestamp": "159", "id": "159", "name": "159.txt"}, {"timestamp": "160", "id": "160", "name": "160.txt"}, {"timestamp": "161", "id": "161", "name": "161.txt"}, {"timestamp": "162", "id": "162", "name": "162.txt"}, {"timestamp": "163", "id": "163", "name": "163.txt"}, {"timestamp": "164", "id": "164", "name": "164.txt"}, {"timestamp": "165", "id": "165", "name": "165.txt"}, {"timestamp": "166", "id": "166", "name": "166.txt"}, {"timestamp": "167", "id": "167", "name": "167.txt"}, {"timestamp": "168", "id": "168", "name": "168.txt"}, {"timestamp": "169", "id": "169", "name": "169.txt"}, {"timestamp": "170", "id": "170", "name": "170.txt"}, {"timestamp": "171", "id": "171", "name": "171.txt"}, {"timestamp": "172", "id": "172", "name": "172.txt"}, {"timestamp": "173", "id": "173", "name": "173.txt"}, {"timestamp": "174", "id": "174", "name": "174.txt"}, {"timestamp": "175", "id": "175", "name": "175.txt"}, {"timestamp": "176", "id": "176", "name": "176.txt"}, {"timestamp": "177", "id": "177", "name": "177.txt"}, {"timestamp": "178", "id": "178", "name": "178.txt"}, {"timestamp": "179", "id": "179", "name": "179.txt"}, {"timestamp": "180", "id": "180", "name": "180.txt"}, {"timestamp": "181", "id": "181", "name": "181.txt"}, {"timestamp": "182", "id": "182", "name": "182.txt"}, {"timestamp": "183", "id": "183", "name": "183.txt"}, {"timestamp": "184", "id": "184", "name": "184.txt"}, {"timestamp": "185", "id": "185", "name": "185.txt"}, {"timestamp": "186", "id": "186", "name": "186.txt"}, {"timestamp": "187", "id": "187", "name": "187.txt"}, {"timestamp": "188", "id": "188", "name": "188.txt"}, {"timestamp": "189", "id": "189", "name": "189.txt"}, {"timestamp": "190", "id": "190", "name": "190.txt"}, {"timestamp": "191", "id": "191", "name": "191.txt"}, {"timestamp": "192", "id": "192", "name": "192.txt"}, {"timestamp": "193", "id": "193", "name": "193.txt"}, {"timestamp": "194", "id": "194", "name": "194.txt"}, {"timestamp": "195", "id": "195", "name": "195.txt"}, {"timestamp": "196", "id": "196", "name": "196.txt"}, {"timestamp": "197", "id": "197", "name": "197.txt"}, {"timestamp": "198", "id": "198", "name": "198.txt"}, {"timestamp": "199", "id": "199", "name": "199.txt"}, {"timestamp": "200", "id": "200", "name": "200.txt"}, {"timestamp": "201", "id": "201", "name": "201.txt"}, {"timestamp": "202", "id": "202", "name": "202.txt"}, {"timestamp": "203", "id": "203", "name": "203.txt"}, {"timestamp": "204", "id": "204", "name": "204.txt"}, {"timestamp": "205", "id": "205", "name": "205.txt"}, {"timestamp": "206", "id": "206", "name": "206.txt"}, {"timestamp": "207", "id": "207", "name": "207.txt"}, {"timestamp": "208", "id": "208", "name": "208.txt"}, {"timestamp": "209", "id": "209", "name": "209.txt"}, {"timestamp": "210", "id": "210", "name": "210.txt"}, {"timestamp": "211", "id": "211", "name": "211.txt"}, {"timestamp": "212", "id": "212", "name": "212.txt"}, {"timestamp": "213", "id": "213", "name": "213.txt"}, {"timestamp": "214", "id": "214", "name": "214.txt"}, {"timestamp": "215", "id": "215", "name": "215.txt"}, {"timestamp": "216", "id": "216", "name": "216.txt"}, {"timestamp": "217", "id": "217", "name": "217.txt"}, {"timestamp": "218", "id": "218", "name": "218.txt"}, {"timestamp": "219", "id": "219", "name": "219.txt"}, {"timestamp": "220", "id": "220", "name": "220.txt"}, {"timestamp": "221", "id": "221", "name": "221.txt"}, {"timestamp": "222", "id": "222", "name": "222.txt"}, {"timestamp": "223", "id": "223", "name": "223.txt"}, {"timestamp": "224", "id": "224", "name": "224.txt"}, {"timestamp": "225", "id": "225", "name": "225.txt"}, {"timestamp": "226", "id": "226", "name": "226.txt"}, {"timestamp": "227", "id": "227", "name": "227.txt"}, {"timestamp": "228", "id": "228", "name": "228.txt"}, {"timestamp": "229", "id": "229", "name": "229.txt"}, {"timestamp": "230", "id": "230", "name": "230.txt"}, {"timestamp": "231", "id": "231", "name": "231.txt"}, {"timestamp": "232", "id": "232", "name": "232.txt"}, {"timestamp": "233", "id": "233", "name": "233.txt"}, {"timestamp": "234", "id": "234", "name": "234.txt"}, {"timestamp": "235", "id": "235", "name": "235.txt"}, {"timestamp": "236", "id": "236", "name": "236.txt"}, {"timestamp": "237", "id": "237", "name": "237.txt"}, {"timestamp": "238", "id": "238", "name": "238.txt"}, {"timestamp": "239", "id": "239", "name": "239.txt"}, {"timestamp": "240", "id": "240", "name": "240.txt"}, {"timestamp": "241", "id": "241", "name": "241.txt"}, {"timestamp": "242", "id": "242", "name": "242.txt"}, {"timestamp": "243", "id": "243", "name": "243.txt"}, {"timestamp": "244", "id": "244", "name": "244.txt"}, {"timestamp": "245", "id": "245", "name": "245.txt"}, {"timestamp": "246", "id": "246", "name": "246.txt"}, {"timestamp": "247", "id": "247", "name": "247.txt"}, {"timestamp": "248", "id": "248", "name": "248.txt"}, {"timestamp": "249", "id": "249", "name": "249.txt"}, {"timestamp": "250", "id": "250", "name": "250.txt"}, {"timestamp": "251", "id": "251", "name": "251.txt"}, {"timestamp": "252", "id": "252", "name": "252.txt"}, {"timestamp": "253", "id": "253", "name": "253.txt"}, {"timestamp": "254", "id": "254", "name": "254.txt"}, {"timestamp": "255", "id": "255", "name": "255.txt"}, {"timestamp": "256", "id": "256", "name": "256.txt"}, {"timestamp": "257", "id": "257", "name": "257.txt"}, {"timestamp": "258", "id": "258", "name": "258.txt"}, {"timestamp": "259", "id": "259", "name": "259.txt"}, {"timestamp": "260", "id": "260", "name": "260.txt"}, {"timestamp": "261", "id": "261", "name": "261.txt"}, {"timestamp": "262", "id": "262", "name": "262.txt"}, {"timestamp": "263", "id": "263", "name": "263.txt"}, {"timestamp": "264", "id": "264", "name": "264.txt"}, {"timestamp": "265", "id": "265", "name": "265.txt"}, {"timestamp": "266", "id": "266", "name": "266.txt"}, {"timestamp": "267", "id": "267", "name": "267.txt"}, {"timestamp": "268", "id": "268", "name": "268.txt"}, {"timestamp": "269", "id": "269", "name": "269.txt"}, {"timestamp": "270", "id": "270", "name": "270.txt"}, {"timestamp": "271", "id": "271", "name": "271.txt"}, {"timestamp": "272", "id": "272", "name": "272.txt"}, {"timestamp": "273", "id": "273", "name": "273.txt"}, {"timestamp": "274", "id": "274", "name": "274.txt"}, {"timestamp": "275", "id": "275", "name": "275.txt"}, {"timestamp": "276", "id": "276", "name": "276.txt"}, {"timestamp": "277", "id": "277", "name": "277.txt"}, {"timestamp": "278", "id": "278", "name": "278.txt"}, {"timestamp": "279", "id": "279", "name": "279.txt"}, {"timestamp": "280", "id": "280", "name": "280.txt"}, {"timestamp": "281", "id": "281", "name": "281.txt"}, {"timestamp": "282", "id": "282", "name": "282.txt"}, {"timestamp": "283", "id": "283", "name": "283.txt"}, {"timestamp": "284", "id": "284", "name": "284.txt"}, {"timestamp": "285", "id": "285", "name": "285.txt"}, {"timestamp": "286", "id": "286", "name": "286.txt"}, {"timestamp": "287", "id": "287", "name": "287.txt"}, {"timestamp": "288", "id": "288", "name": "288.txt"}, {"timestamp": "289", "id": "289", "name": "289.txt"}, {"timestamp": "290", "id": "290", "name": "290.txt"}, {"timestamp": "291", "id": "291", "name": "291.txt"}, {"timestamp": "292", "id": "292", "name": "292.txt"}, {"timestamp": "293", "id": "293", "name": "293.txt"}, {"timestamp": "294", "id": "294", "name": "294.txt"}, {"timestamp": "295", "id": "295", "name": "295.txt"}, {"timestamp": "296", "id": "296", "name": "296.txt"}, {"timestamp": "297", "id": "297", "name": "297.txt"}, {"timestamp": "298", "id": "298", "name": "298.txt"}, {"timestamp": "299", "id": "299", "name": "299.txt"}, {"timestamp": "300", "id": "300", "name": "300.txt"}, {"timestamp": "301", "id": "301", "name": "301.txt"}, {"timestamp": "302", "id": "302", "name": "302.txt"}, {"timestamp": "303", "id": "303", "name": "303.txt"}, {"timestamp": "304", "id": "304", "name": "304.txt"}, {"timestamp": "305", "id": "305", "name": "305.txt"}, {"timestamp": "306", "id": "306", "name": "306.txt"}, {"timestamp": "307", "id": "307", "name": "307.txt"}, {"timestamp": "308", "id": "308", "name": "308.txt"}, {"timestamp": "309", "id": "309", "name": "309.txt"}, {"timestamp": "310", "id": "310", "name": "310.txt"}, {"timestamp": "311", "id": "311", "name": "311.txt"}, {"timestamp": "312", "id": "312", "name": "312.txt"}, {"timestamp": "313", "id": "313", "name": "313.txt"}, {"timestamp": "314", "id": "314", "name": "314.txt"}, {"timestamp": "315", "id": "315", "name": "315.txt"}, {"timestamp": "316", "id": "316", "name": "316.txt"}, {"timestamp": "317", "id": "317", "name": "317.txt"}, {"timestamp": "318", "id": "318", "name": "318.txt"}, {"timestamp": "319", "id": "319", "name": "319.txt"}, {"timestamp": "320", "id": "320", "name": "320.txt"}, {"timestamp": "321", "id": "321", "name": "321.txt"}, {"timestamp": "322", "id": "322", "name": "322.txt"}, {"timestamp": "323", "id": "323", "name": "323.txt"}, {"timestamp": "324", "id": "324", "name": "324.txt"}, {"timestamp": "325", "id": "325", "name": "325.txt"}, {"timestamp": "326", "id": "326", "name": "326.txt"}, {"timestamp": "327", "id": "327", "name": "327.txt"}, {"timestamp": "328", "id": "328", "name": "328.txt"}, {"timestamp": "329", "id": "329", "name": "329.txt"}, {"timestamp": "330", "id": "330", "name": "330.txt"}, {"timestamp": "331", "id": "331", "name": "331.txt"}, {"timestamp": "332", "id": "332", "name": "332.txt"}, {"timestamp": "333", "id": "333", "name": "333.txt"}, {"timestamp": "334", "id": "334", "name": "334.txt"}, {"timestamp": "335", "id": "335", "name": "335.txt"}, {"timestamp": "336", "id": "336", "name": "336.txt"}, {"timestamp": "337", "id": "337", "name": "337.txt"}, {"timestamp": "338", "id": "338", "name": "338.txt"}, {"timestamp": "339", "id": "339", "name": "339.txt"}, {"timestamp": "340", "id": "340", "name": "340.txt"}, {"timestamp": "341", "id": "341", "name": "341.txt"}, {"timestamp": "342", "id": "342", "name": "342.txt"}, {"timestamp": "343", "id": "343", "name": "343.txt"}, {"timestamp": "344", "id": "344", "name": "344.txt"}, {"timestamp": "345", "id": "345", "name": "345.txt"}, {"timestamp": "346", "id": "346", "name": "346.txt"}, {"timestamp": "347", "id": "347", "name": "347.txt"}, {"timestamp": "348", "id": "348", "name": "348.txt"}, {"timestamp": "349", "id": "349", "name": "349.txt"}, {"timestamp": "350", "id": "350", "name": "350.txt"}, {"timestamp": "351", "id": "351", "name": "351.txt"}, {"timestamp": "352", "id": "352", "name": "352.txt"}, {"timestamp": "353", "id": "353", "name": "353.txt"}, {"timestamp": "354", "id": "354", "name": "354.txt"}, {"timestamp": "355", "id": "355", "name": "355.txt"}, {"timestamp": "356", "id": "356", "name": "356.txt"}, {"timestamp": "357", "id": "357", "name": "357.txt"}, {"timestamp": "358", "id": "358", "name": "358.txt"}, {"timestamp": "359", "id": "359", "name": "359.txt"}, {"timestamp": "360", "id": "360", "name": "360.txt"}, {"timestamp": "361", "id": "361", "name": "361.txt"}, {"timestamp": "362", "id": "362", "name": "362.txt"}, {"timestamp": "363", "id": "363", "name": "363.txt"}, {"timestamp": "364", "id": "364", "name": "364.txt"}, {"timestamp": "365", "id": "365", "name": "365.txt"}, {"timestamp": "366", "id": "366", "name": "366.txt"}, {"timestamp": "367", "id": "367", "name": "367.txt"}, {"timestamp": "368", "id": "368", "name": "368.txt"}, {"timestamp": "369", "id": "369", "name": "369.txt"}, {"timestamp": "370", "id": "370", "name": "370.txt"}, {"timestamp": "371", "id": "371", "name": "371.txt"}, {"timestamp": "372", "id": "372", "name": "372.txt"}, {"timestamp": "373", "id": "373", "name": "373.txt"}, {"timestamp": "374", "id": "374", "name": "374.txt"}, {"timestamp": "375", "id": "375", "name": "375.txt"}, {"timestamp": "376", "id": "376", "name": "376.txt"}, {"timestamp": "377", "id": "377", "name": "377.txt"}, {"timestamp": "378", "id": "378", "name": "378.txt"}, {"timestamp": "379", "id": "379", "name": "379.txt"}, {"timestamp": "380", "id": "380", "name": "380.txt"}, {"timestamp": "381", "id": "381", "name": "381.txt"}, {"timestamp": "382", "id": "382", "name": "382.txt"}, {"timestamp": "383", "id": "383", "name": "383.txt"}, {"timestamp": "384", "id": "384", "name": "384.txt"}, {"timestamp": "385", "id": "385", "name": "385.txt"}, {"timestamp": "386", "id": "386", "name": "386.txt"}, {"timestamp": "387", "id": "387", "name": "387.txt"}, {"timestamp": "388", "id": "388", "name": "388.txt"}, {"timestamp": "389", "id": "389", "name": "389.txt"}, {"timestamp": "390", "id": "390", "name": "390.txt"}, {"timestamp": "391", "id": "391", "name": "391.txt"}, {"timestamp": "392", "id": "392", "name": "392.txt"}, {"timestamp": "393", "id": "393", "name": "393.txt"}, {"timestamp": "394", "id": "394", "name": "394.txt"}, {"timestamp": "395", "id": "395", "name": "395.txt"}, {"timestamp": "396", "id": "396", "name": "396.txt"}, {"timestamp": "397", "id": "397", "name": "397.txt"}, {"timestamp": "398", "id": "398", "name": "398.txt"}, {"timestamp": "399", "id": "399", "name": "399.txt"}, {"timestamp": "400", "id": "400", "name": "400.txt"}, {"timestamp": "401", "id": "401", "name": "401.txt"}, {"timestamp": "402", "id": "402", "name": "402.txt"}, {"timestamp": "403", "id": "403", "name": "403.txt"}, {"timestamp": "404", "id": "404", "name": "404.txt"}, {"timestamp": "405", "id": "405", "name": "405.txt"}, {"timestamp": "406", "id": "406", "name": "406.txt"}, {"timestamp": "407", "id": "407", "name": "407.txt"}, {"timestamp": "408", "id": "408", "name": "408.txt"}, {"timestamp": "409", "id": "409", "name": "409.txt"}, {"timestamp": "410", "id": "410", "name": "410.txt"}, {"timestamp": "411", "id": "411", "name": "411.txt"}, {"timestamp": "412", "id": "412", "name": "412.txt"}, {"timestamp": "413", "id": "413", "name": "413.txt"}, {"timestamp": "414", "id": "414", "name": "414.txt"}, {"timestamp": "415", "id": "415", "name": "415.txt"}, {"timestamp": "416", "id": "416", "name": "416.txt"}, {"timestamp": "417", "id": "417", "name": "417.txt"}, {"timestamp": "418", "id": "418", "name": "418.txt"}, {"timestamp": "419", "id": "419", "name": "419.txt"}, {"timestamp": "420", "id": "420", "name": "420.txt"}, {"timestamp": "421", "id": "421", "name": "421.txt"}, {"timestamp": "422", "id": "422", "name": "422.txt"}, {"timestamp": "423", "id": "423", "name": "423.txt"}, {"timestamp": "424", "id": "424", "name": "424.txt"}, {"timestamp": "425", "id": "425", "name": "425.txt"}, {"timestamp": "426", "id": "426", "name": "426.txt"}, {"timestamp": "427", "id": "427", "name": "427.txt"}, {"timestamp": "428", "id": "428", "name": "428.txt"}, {"timestamp": "429", "id": "429", "name": "429.txt"}, {"timestamp": "430", "id": "430", "name": "430.txt"}, {"timestamp": "431", "id": "431", "name": "431.txt"}, {"timestamp": "432", "id": "432", "name": "432.txt"}, {"timestamp": "433", "id": "433", "name": "433.txt"}, {"timestamp": "434", "id": "434", "name": "434.txt"}, {"timestamp": "435", "id": "435", "name": "435.txt"}, {"timestamp": "436", "id": "436", "name": "436.txt"}, {"timestamp": "437", "id": "437", "name": "437.txt"}, {"timestamp": "438", "id": "438", "name": "438.txt"}, {"timestamp": "439", "id": "439", "name": "439.txt"}, {"timestamp": "440", "id": "440", "name": "440.txt"}, {"timestamp": "441", "id": "441", "name": "441.txt"}, {"timestamp": "442", "id": "442", "name": "442.txt"}, {"timestamp": "443", "id": "443", "name": "443.txt"}, {"timestamp": "444", "id": "444", "name": "444.txt"}, {"timestamp": "445", "id": "445", "name": "445.txt"}, {"timestamp": "446", "id": "446", "name": "446.txt"}, {"timestamp": "447", "id": "447", "name": "447.txt"}, {"timestamp": "448", "id": "448", "name": "448.txt"}, {"timestamp": "449", "id": "449", "name": "449.txt"}, {"timestamp": "450", "id": "450", "name": "450.txt"}, {"timestamp": "451", "id": "451", "name": "451.txt"}, {"timestamp": "452", "id": "452", "name": "452.txt"}, {"timestamp": "453", "id": "453", "name": "453.txt"}, {"timestamp": "454", "id": "454", "name": "454.txt"}, {"timestamp": "455", "id": "455", "name": "455.txt"}, {"timestamp": "456", "id": "456", "name": "456.txt"}, {"timestamp": "457", "id": "457", "name": "457.txt"}, {"timestamp": "458", "id": "458", "name": "458.txt"}, {"timestamp": "459", "id": "459", "name": "459.txt"}, {"timestamp": "460", "id": "460", "name": "460.txt"}, {"timestamp": "461", "id": "461", "name": "461.txt"}, {"timestamp": "462", "id": "462", "name": "462.txt"}, {"timestamp": "463", "id": "463", "name": "463.txt"}, {"timestamp": "464", "id": "464", "name": "464.txt"}, {"timestamp": "465", "id": "465", "name": "465.txt"}, {"timestamp": "466", "id": "466", "name": "466.txt"}, {"timestamp": "467", "id": "467", "name": "467.txt"}, {"timestamp": "468", "id": "468", "name": "468.txt"}, {"timestamp": "469", "id": "469", "name": "469.txt"}, {"timestamp": "470", "id": "470", "name": "470.txt"}, {"timestamp": "471", "id": "471", "name": "471.txt"}, {"timestamp": "472", "id": "472", "name": "472.txt"}, {"timestamp": "473", "id": "473", "name": "473.txt"}, {"timestamp": "474", "id": "474", "name": "474.txt"}, {"timestamp": "475", "id": "475", "name": "475.txt"}, {"timestamp": "476", "id": "476", "name": "476.txt"}, {"timestamp": "477", "id": "477", "name": "477.txt"}, {"timestamp": "478", "id": "478", "name": "478.txt"}, {"timestamp": "479", "id": "479", "name": "479.txt"}, {"timestamp": "480", "id": "480", "name": "480.txt"}, {"timestamp": "481", "id": "481", "name": "481.txt"}, {"timestamp": "482", "id": "482", "name": "482.txt"}, {"timestamp": "483", "id": "483", "name": "483.txt"}, {"timestamp": "484", "id": "484", "name": "484.txt"}, {"timestamp": "485", "id": "485", "name": "485.txt"}, {"timestamp": "486", "id": "486", "name": "486.txt"}, {"timestamp": "487", "id": "487", "name": "487.txt"}, {"timestamp": "488", "id": "488", "name": "488.txt"}, {"timestamp": "489", "id": "489", "name": "489.txt"}, {"timestamp": "490", "id": "490", "name": "490.txt"}, {"timestamp": "491", "id": "491", "name": "491.txt"}, {"timestamp": "492", "id": "492", "name": "492.txt"}, {"timestamp": "493", "id": "493", "name": "493.txt"}, {"timestamp": "494", "id": "494", "name": "494.txt"}, {"timestamp": "495", "id": "495", "name": "495.txt"}, {"timestamp": "496", "id": "496", "name": "496.txt"}, {"timestamp": "497", "id": "497", "name": "497.txt"}, {"timestamp": "498", "id": "498", "name": "498.txt"}, {"timestamp": "499", "id": "499", "name": "499.txt"}, {"timestamp": "500", "id": "500", "name": "500.txt"}, {"timestamp": "501", "id": "501", "name": "501.txt"}, {"timestamp": "502", "id": "502", "name": "502.txt"}, {"timestamp": "503", "id": "503", "name": "503.txt"}, {"timestamp": "504", "id": "504", "name": "504.txt"}, {"timestamp": "505", "id": "505", "name": "505.txt"}, {"timestamp": "506", "id": "506", "name": "506.txt"}, {"timestamp": "507", "id": "507", "name": "507.txt"}, {"timestamp": "508", "id": "508", "name": "508.txt"}, {"timestamp": "509", "id": "509", "name": "509.txt"}, {"timestamp": "510", "id": "510", "name": "510.txt"}, {"timestamp": "511", "id": "511", "name": "511.txt"}, {"timestamp": "512", "id": "512", "name": "512.txt"}, {"timestamp": "513", "id": "513", "name": "513.txt"}, {"timestamp": "514", "id": "514", "name": "514.txt"}, {"timestamp": "515", "id": "515", "name": "515.txt"}, {"timestamp": "516", "id": "516", "name": "516.txt"}, {"timestamp": "517", "id": "517", "name": "517.txt"}, {"timestamp": "518", "id": "518", "name": "518.txt"}, {"timestamp": "519", "id": "519", "name": "519.txt"}, {"timestamp": "520", "id": "520", "name": "520.txt"}, {"timestamp": "521", "id": "521", "name": "521.txt"}, {"timestamp": "522", "id": "522", "name": "522.txt"}, {"timestamp": "523", "id": "523", "name": "523.txt"}, {"timestamp": "524", "id": "524", "name": "524.txt"}, {"timestamp": "525", "id": "525", "name": "525.txt"}, {"timestamp": "526", "id": "526", "name": "526.txt"}, {"timestamp": "527", "id": "527", "name": "527.txt"}, {"timestamp": "528", "id": "528", "name": "528.txt"}, {"timestamp": "529", "id": "529", "name": "529.txt"}, {"timestamp": "530", "id": "530", "name": "530.txt"}, {"timestamp": "531", "id": "531", "name": "531.txt"}, {"timestamp": "532", "id": "532", "name": "532.txt"}, {"timestamp": "533", "id": "533", "name": "533.txt"}, {"timestamp": "534", "id": "534", "name": "534.txt"}, {"timestamp": "535", "id": "535", "name": "535.txt"}, {"timestamp": "536", "id": "536", "name": "536.txt"}, {"timestamp": "537", "id": "537", "name": "537.txt"}, {"timestamp": "538", "id": "538", "name": "538.txt"}, {"timestamp": "539", "id": "539", "name": "539.txt"}, {"timestamp": "540", "id": "540", "name": "540.txt"}, {"timestamp": "541", "id": "541", "name": "541.txt"}]